trytond/modules/health_ophthalmology/COPYING
trytond/modules/health_ophthalmology/README.rst
trytond/modules/health_ophthalmology/__init__.py
trytond/modules/health_ophthalmology/health_ophthalmology.py
trytond/modules/health_ophthalmology/health_ophthalmology_report.xml
trytond/modules/health_ophthalmology/health_ophthalmology_view.xml
trytond/modules/health_ophthalmology/icons/ophthalmology.svg
trytond/modules/health_ophthalmology/locale/ar.po
trytond/modules/health_ophthalmology/locale/de.po
trytond/modules/health_ophthalmology/locale/el.po
trytond/modules/health_ophthalmology/locale/eo.po
trytond/modules/health_ophthalmology/locale/es.po
trytond/modules/health_ophthalmology/locale/fr.po
trytond/modules/health_ophthalmology/locale/health_ophthalmology.pot
trytond/modules/health_ophthalmology/locale/it_IT.po
trytond/modules/health_ophthalmology/locale/ja_JP.po
trytond/modules/health_ophthalmology/locale/ka.po
trytond/modules/health_ophthalmology/locale/lo.po
trytond/modules/health_ophthalmology/locale/pt_BR.po
trytond/modules/health_ophthalmology/locale/sv.po
trytond/modules/health_ophthalmology/locale/tr.po
trytond/modules/health_ophthalmology/locale/uk.po
trytond/modules/health_ophthalmology/locale/zh_CN.po
trytond/modules/health_ophthalmology/pyproject.toml
trytond/modules/health_ophthalmology/report/ophthalmology.fodt
trytond/modules/health_ophthalmology/tests/__init__.py
trytond/modules/health_ophthalmology/tests/test_health_ophthalmology.py
trytond/modules/health_ophthalmology/tryton.cfg
trytond/modules/health_ophthalmology/view/findings_form.xml
trytond/modules/health_ophthalmology/view/findings_tree.xml
trytond/modules/health_ophthalmology/view/oph_form.xml
trytond/modules/health_ophthalmology/view/oph_tree.xml
gnuhealth_ophthalmology-5.0.2.dist-info/METADATA
gnuhealth_ophthalmology-5.0.2.dist-info/WHEEL
gnuhealth_ophthalmology-5.0.2.dist-info/licenses/COPYING
gnuhealth_ophthalmology-5.0.2.dist-info/RECORD
